{"id": 1043, "name": "Parque Nacional Arrecife Alacranes", "location_type": "wdpa", "iso": "MEX", "bounds": {"coordinates": [[[-90.00777970160553, 22.150276762066035], [-89.40111010489922, 22.150276762066035], [-89.40111010489922, 22.798888704646803], [-90.00777970160553, 22.798888704646803], [-90.00777970160553, 22.150276762066035]]], "geodesic": false, "type": "Polygon"}, "area_m2": 3345054811.4887, "perimeter_m": 207629.711342802, "location_id": "2_000000000000000007a6", "coast_length_m": 9072.98, "geometry": {"type": "Polygon", "coordinates": [[[-90.00777970160553, 22.564723453725364], [-90.00166628233458, 22.46055438979107], [-89.95166633666004, 22.373334415119626], [-89.9022238792239, 22.289168846219248], [-89.83333518356446, 22.218331635537403], [-89.74694456302534, 22.16666846147486], [-89.64638737649304, 22.15027676206606], [-89.5533348648018, 22.183613075673232], [-89.4741679671348, 22.24111315651452], [-89.42388716194138, 22.32694639341272], [-89.40111010489922, 22.42749909021232], [-89.40777641665873, 22.5255547479756], [-89.44999965632144, 22.61722045078604], [-89.50611296456803, 22.698612493592545], [-89.58666664657468, 22.756112573765222], [-89.67833242235119, 22.79222233129078], [-89.72111298605031, 22.798888704646778], [-89.82222310215347, 22.782778028175244], [-89.90416805790773, 22.72944267322126], [-89.97138898071292, 22.654168591381417], [-90.00777970160553, 22.564723453725364]]]}, "mangrove_datum": [{"id": 28221, "date": "2000-01-01", "gain_m2": null, "loss_m2": null, "net_change_m2": 0.0, "length_m": null, "area_m2": null, "hmax_m": 0.0, "agb_mgha_1": 0.0, "hba_m": null, "agb_hist_mgha_1": [[0, 0], [10, 0], [20, 0], [30, 0], [40, 0], [50, 0], [60, 0], [70, 0], [80, 0], [90, 0], [100, 0], [110, 0], [120, 0], [130, 0], [140, 0], [150, 0], [160, 0], [170, 0], [180, 0], [190, 0], [200, 0], [210, 0], [220, 0], [230, 0], [240, 0], [250, 0]], "con_hotspot_summary_km2": {"LT_advice": "NA", "MT_advice": "NA", "ST_advice": "NA"}, "hba_hist_m": null, "hmax_hist_m": [[0, 0], [1, 0], [2, 0], [3, 0], [4, 0], [5, 0], [6, 0], [7, 0], [8, 0], [9, 0], [10, 0], [11, 0], [12, 0], [13, 0], [14, 0], [15, 0], [16, 0], [17, 0], [18, 0], [19, 0], [20, 0], [21, 0], [22, 0], [23, 0], [24, 0], [25, 0]], "agb_tco2e": null, "bgb_tco2e": null, "soc_tco2e": null, "toc_tco2e": null, "toc_hist_tco2eha": null}, {"id": 28220, "date": "1996-01-01", "gain_m2": null, "loss_m2": null, "net_change_m2": 0.0, "length_m": 0.0, "area_m2": 0.0, "hmax_m": 0.0, "agb_mgha_1": 0.0, "hba_m": null, "agb_hist_mgha_1": [[0, 0], [10, 0], [20, 0], [30, 0], [40, 0], [50, 0], [60, 0], [70, 0], [80, 0], [90, 0], [100, 0], [110, 0], [120, 0], [130, 0], [140, 0], [150, 0], [160, 0], [170, 0], [180, 0], [190, 0], [200, 0], [210, 0], [220, 0], [230, 0], [240, 0], [250, 0]], "con_hotspot_summary_km2": {"LT_advice": "NA", "MT_advice": "NA", "ST_advice": "NA"}, "hba_hist_m": null, "hmax_hist_m": [[0, 0], [1, 0], [2, 0], [3, 0], [4, 0], [5, 0], [6, 0], [7, 0], [8, 0], [9, 0], [10, 0], [11, 0], [12, 0], [13, 0], [14, 0], [15, 0], [16, 0], [17, 0], [18, 0], [19, 0], [20, 0], [21, 0], [22, 0], [23, 0], [24, 0], [25, 0]], "agb_tco2e": null, "bgb_tco2e": null, "soc_tco2e": null, "toc_tco2e": null, "toc_hist_tco2eha": null}, {"id": 28219, "date": "2016-01-01", "gain_m2": 0.0, "loss_m2": 0.0, "net_change_m2": 0.0, "length_m": 0.0, "area_m2": 0.0, "hmax_m": 0.0, "agb_mgha_1": 0.0, "hba_m": null, "agb_hist_mgha_1": [[0, 0], [10, 0], [20, 0], [30, 0], [40, 0], [50, 0], [60, 0], [70, 0], [80, 0], [90, 0], [100, 0], [110, 0], [120, 0], [130, 0], [140, 0], [150, 0], [160, 0], [170, 0], [180, 0], [190, 0], [200, 0], [210, 0], [220, 0], [230, 0], [240, 0], [250, 0]], "con_hotspot_summary_km2": {"LT_advice": "NA", "MT_advice": "NA", "ST_advice": "NA"}, "hba_hist_m": null, "hmax_hist_m": [[0, 0], [1, 0], [2, 0], [3, 0], [4, 0], [5, 0], [6, 0], [7, 0], [8, 0], [9, 0], [10, 0], [11, 0], [12, 0], [13, 0], [14, 0], [15, 0], [16, 0], [17, 0], [18, 0], [19, 0], [20, 0], [21, 0], [22, 0], [23, 0], [24, 0], [25, 0]], "agb_tco2e": 0.0, "bgb_tco2e": 0.0, "soc_tco2e": 0.0, "toc_tco2e": 0.0, "toc_hist_tco2eha": {"1000--1300": 0, "1300--1600": 0, "1600--1900": 0, "1900--2200": 0, "400--700": 0, "700--1000": 0}}, {"id": 28218, "date": "2015-01-01", "gain_m2": 0.0, "loss_m2": 0.0, "net_change_m2": 0.0, "length_m": 0.0, "area_m2": 0.0, "hmax_m": 0.0, "agb_mgha_1": 0.0, "hba_m": null, "agb_hist_mgha_1": [[0, 0], [10, 0], [20, 0], [30, 0], [40, 0], [50, 0], [60, 0], [70, 0], [80, 0], [90, 0], [100, 0], [110, 0], [120, 0], [130, 0], [140, 0], [150, 0], [160, 0], [170, 0], [180, 0], [190, 0], [200, 0], [210, 0], [220, 0], [230, 0], [240, 0], [250, 0]], "con_hotspot_summary_km2": {"LT_advice": "NA", "MT_advice": "NA", "ST_advice": "NA"}, "hba_hist_m": null, "hmax_hist_m": [[0, 0], [1, 0], [2, 0], [3, 0], [4, 0], [5, 0], [6, 0], [7, 0], [8, 0], [9, 0], [10, 0], [11, 0], [12, 0], [13, 0], [14, 0], [15, 0], [16, 0], [17, 0], [18, 0], [19, 0], [20, 0], [21, 0], [22, 0], [23, 0], [24, 0], [25, 0]], "agb_tco2e": null, "bgb_tco2e": null, "soc_tco2e": null, "toc_tco2e": null, "toc_hist_tco2eha": null}, {"id": 28217, "date": "2010-01-01", "gain_m2": 0.0, "loss_m2": 0.0, "net_change_m2": 0.0, "length_m": 0.0, "area_m2": 0.0, "hmax_m": 0.0, "agb_mgha_1": 0.0, "hba_m": null, "agb_hist_mgha_1": [[0, 0], [10, 0], [20, 0], [30, 0], [40, 0], [50, 0], [60, 0], [70, 0], [80, 0], [90, 0], [100, 0], [110, 0], [120, 0], [130, 0], [140, 0], [150, 0], [160, 0], [170, 0], [180, 0], [190, 0], [200, 0], [210, 0], [220, 0], [230, 0], [240, 0], [250, 0]], "con_hotspot_summary_km2": {"LT_advice": "NA", "MT_advice": "NA", "ST_advice": "NA"}, "hba_hist_m": null, "hmax_hist_m": [[0, 0], [1, 0], [2, 0], [3, 0], [4, 0], [5, 0], [6, 0], [7, 0], [8, 0], [9, 0], [10, 0], [11, 0], [12, 0], [13, 0], [14, 0], [15, 0], [16, 0], [17, 0], [18, 0], [19, 0], [20, 0], [21, 0], [22, 0], [23, 0], [24, 0], [25, 0]], "agb_tco2e": null, "bgb_tco2e": null, "soc_tco2e": null, "toc_tco2e": null, "toc_hist_tco2eha": null}, {"id": 28216, "date": "2009-01-01", "gain_m2": 0.0, "loss_m2": 0.0, "net_change_m2": 0.0, "length_m": 0.0, "area_m2": 0.0, "hmax_m": 0.0, "agb_mgha_1": 0.0, "hba_m": null, "agb_hist_mgha_1": [[0, 0], [10, 0], [20, 0], [30, 0], [40, 0], [50, 0], [60, 0], [70, 0], [80, 0], [90, 0], [100, 0], [110, 0], [120, 0], [130, 0], [140, 0], [150, 0], [160, 0], [170, 0], [180, 0], [190, 0], [200, 0], [210, 0], [220, 0], [230, 0], [240, 0], [250, 0]], "con_hotspot_summary_km2": {"LT_advice": "NA", "MT_advice": "NA", "ST_advice": "NA"}, "hba_hist_m": null, "hmax_hist_m": [[0, 0], [1, 0], [2, 0], [3, 0], [4, 0], [5, 0], [6, 0], [7, 0], [8, 0], [9, 0], [10, 0], [11, 0], [12, 0], [13, 0], [14, 0], [15, 0], [16, 0], [17, 0], [18, 0], [19, 0], [20, 0], [21, 0], [22, 0], [23, 0], [24, 0], [25, 0]], "agb_tco2e": null, "bgb_tco2e": null, "soc_tco2e": null, "toc_tco2e": null, "toc_hist_tco2eha": null}, {"id": 28215, "date": "2008-01-01", "gain_m2": 0.0, "loss_m2": 0.0, "net_change_m2": 0.0, "length_m": 0.0, "area_m2": 0.0, "hmax_m": 0.0, "agb_mgha_1": 0.0, "hba_m": null, "agb_hist_mgha_1": [[0, 0], [10, 0], [20, 0], [30, 0], [40, 0], [50, 0], [60, 0], [70, 0], [80, 0], [90, 0], [100, 0], [110, 0], [120, 0], [130, 0], [140, 0], [150, 0], [160, 0], [170, 0], [180, 0], [190, 0], [200, 0], [210, 0], [220, 0], [230, 0], [240, 0], [250, 0]], "con_hotspot_summary_km2": {"LT_advice": "NA", "MT_advice": "NA", "ST_advice": "NA"}, "hba_hist_m": null, "hmax_hist_m": [[0, 0], [1, 0], [2, 0], [3, 0], [4, 0], [5, 0], [6, 0], [7, 0], [8, 0], [9, 0], [10, 0], [11, 0], [12, 0], [13, 0], [14, 0], [15, 0], [16, 0], [17, 0], [18, 0], [19, 0], [20, 0], [21, 0], [22, 0], [23, 0], [24, 0], [25, 0]], "agb_tco2e": null, "bgb_tco2e": null, "soc_tco2e": null, "toc_tco2e": null, "toc_hist_tco2eha": null}, {"id": 28214, "date": "2007-01-01", "gain_m2": 0.0, "loss_m2": 0.0, "net_change_m2": 0.0, "length_m": 0.0, "area_m2": 0.0, "hmax_m": 0.0, "agb_mgha_1": 0.0, "hba_m": null, "agb_hist_mgha_1": [[0, 0], [10, 0], [20, 0], [30, 0], [40, 0], [50, 0], [60, 0], [70, 0], [80, 0], [90, 0], [100, 0], [110, 0], [120, 0], [130, 0], [140, 0], [150, 0], [160, 0], [170, 0], [180, 0], [190, 0], [200, 0], [210, 0], [220, 0], [230, 0], [240, 0], [250, 0]], "con_hotspot_summary_km2": {"LT_advice": "NA", "MT_advice": "NA", "ST_advice": "NA"}, "hba_hist_m": null, "hmax_hist_m": [[0, 0], [1, 0], [2, 0], [3, 0], [4, 0], [5, 0], [6, 0], [7, 0], [8, 0], [9, 0], [10, 0], [11, 0], [12, 0], [13, 0], [14, 0], [15, 0], [16, 0], [17, 0], [18, 0], [19, 0], [20, 0], [21, 0], [22, 0], [23, 0], [24, 0], [25, 0]], "agb_tco2e": null, "bgb_tco2e": null, "soc_tco2e": null, "toc_tco2e": null, "toc_hist_tco2eha": null}]}